tilus/__init__.py
tilus/drivers.py
tilus/logging.py
tilus/option.py
tilus/target.py
tilus/tensor.py
tilus/version.py
tilus/backends/__init__.py
tilus/backends/codegen.py
tilus/backends/emitters/__init__.py
tilus/backends/emitters/allocate.py
tilus/backends/emitters/assign.py
tilus/backends/emitters/cast.py
tilus/backends/emitters/control.py
tilus/backends/emitters/debug.py
tilus/backends/emitters/elementwise.py
tilus/backends/emitters/gmem.py
tilus/backends/emitters/ldst.py
tilus/backends/emitters/reduce.py
tilus/backends/emitters/reduce_old.py
tilus/backends/emitters/shuffle.py
tilus/backends/emitters/smem.py
tilus/backends/emitters/sync.py
tilus/backends/emitters/transform.py
tilus/backends/emitters/view.py
tilus/backends/emitters/where.py
tilus/backends/emitters/cuda/__init__.py
tilus/backends/emitters/cuda/cp_async.py
tilus/backends/emitters/cuda/ldmatrix.py
tilus/backends/emitters/cuda/mma_dot.py
tilus/backends/emitters/cuda/semaphore.py
tilus/backends/emitters/cuda/simt_dot.py
tilus/backends/transforms/__init__.py
tilus/backends/transforms/inline_register_tensor.py
tilus/extensions/__init__.py
tilus/extensions/utils.py
tilus/extensions/hidet/__init__.py
tilus/extensions/hidet/backend/__init__.py
tilus/extensions/hidet/backend/codegen.py
tilus/extensions/hidet/ir/__init__.py
tilus/extensions/hidet/ir/expr.py
tilus/extensions/hidet/ir/module.py
tilus/extensions/hidet/ir/type.py
tilus/extensions/hidet/ir/builders/__init__.py
tilus/extensions/hidet/ir/builders/func_builder.py
tilus/extensions/hidet/ir/builders/stmt_builder.py
tilus/extensions/hidet/ir/dtypes/__init__.py
tilus/extensions/hidet/ir/dtypes/floats.py
tilus/extensions/hidet/ir/dtypes/floats_subbyte.py
tilus/extensions/hidet/ir/dtypes/integer_subbyte.py
tilus/extensions/hidet/ir/dtypes/vector.py
tilus/extensions/hidet/ir/primitives/__init__.py
tilus/extensions/hidet/ir/primitives/debug.py
tilus/extensions/hidet/ir/primitives/runtime.py
tilus/extensions/hidet/ir/primitives/cuda/__init__.py
tilus-0.1.1.dist-info/licenses/LICENSE
tilus-0.1.1.dist-info/METADATA
tilus-0.1.1.dist-info/WHEEL
tilus-0.1.1.dist-info/top_level.txt
tilus-0.1.1.dist-info/RECORD
