Metadata-Version: 2.4
Name: tilus
Version: 0.1.1
Summary: Tilus
Author: Hidet Team
License-Expression: Apache-2.0
Project-URL: Homepage, https://github.com/NVIDIA/tilus
Project-URL: Documentation, https://nvidia.github.io/tilus
Keywords: GPU,Compiler,CUDA,hidet,tensor,torch
Classifier: Development Status :: 4 - Beta
Classifier: Intended Audience :: Developers
Classifier: Intended Audience :: Science/Research
Classifier: Topic :: Scientific/Engineering
Classifier: Topic :: Scientific/Engineering :: Mathematics
Classifier: Topic :: Scientific/Engineering :: Artificial Intelligence
Classifier: Topic :: Software Development
Classifier: Topic :: Software Development :: Libraries
Classifier: Topic :: Software Development :: Libraries :: Python Modules
Classifier: Programming Language :: Python :: 3
Requires-Python: >=3.10
License-File: LICENSE
Requires-Dist: hidet==0.6.1
Requires-Dist: torch
Requires-Dist: tabulate
Provides-Extra: dev
Requires-Dist: ruff==0.11.0; extra == "dev"
Requires-Dist: mypy==1.15.0; extra == "dev"
Requires-Dist: pytest; extra == "dev"
Requires-Dist: types-tabulate; extra == "dev"
Requires-Dist: types-tqdm; extra == "dev"
Requires-Dist: pandas; extra == "dev"
Requires-Dist: nvidia-ml-py; extra == "dev"
Requires-Dist: einops; extra == "dev"
Requires-Dist: jinja2; extra == "dev"
Requires-Dist: sphinx; extra == "dev"
Requires-Dist: sphinx-gallery; extra == "dev"
Requires-Dist: sphinx-copybutton; extra == "dev"
Requires-Dist: autodocsumm; extra == "dev"
Requires-Dist: sphinx-book-theme==1.1.4; extra == "dev"
Requires-Dist: matplotlib; extra == "dev"
Dynamic: license-file
